README.rst
setup.cfg
setup.py
pyofd/__init__.py
pyofd.egg-info/PKG-INFO
pyofd.egg-info/SOURCES.txt
pyofd.egg-info/dependency_links.txt
pyofd.egg-info/not-zip-safe
pyofd.egg-info/requires.txt
pyofd.egg-info/top_level.txt
pyofd/providers/__init__.py
pyofd/providers/base.py
pyofd/providers/dummy.py
pyofd/providers/first_ofd.py
pyofd/providers/kontur.py
pyofd/providers/nalog.py
pyofd/providers/ofd.py
pyofd/providers/platforma.py
pyofd/providers/providers.py
pyofd/providers/sbis.py
pyofd/providers/taxcom.py
pyofd/providers/yandex.py
pyofd/providers/yarus.py
test/test_first_ofd.py
test/test_kontur.py
test/test_nalog.py
test/test_ofd.py
test/test_platforma.py
test/test_providers.py
test/test_taxcom.py
test/test_yandex.py
test/test_yarus.py